securden_sdk/__init__.py
securden_sdk/api_client.py
securden_sdk/api_response.py
securden_sdk/configuration.py
securden_sdk/exceptions.py
securden_sdk/py.typed
securden_sdk/rest.py
securden_sdk/api/__init__.py
securden_sdk/api/default_api.py
securden_sdk/models/__init__.py
securden_sdk/models/get_password_200_response.py
securden_sdk-1.0.1.dist-info/METADATA
securden_sdk-1.0.1.dist-info/WHEEL
securden_sdk-1.0.1.dist-info/entry_points.txt
securden_sdk-1.0.1.dist-info/top_level.txt
securden_sdk-1.0.1.dist-info/RECORD
