Metadata-Version: 2.1
Name: securden-sdk
Version: 1.0.1
Summary: Using functions which use Securden APIs, developers can retrieve credentials programmatically from Securden server.
Home-page: https://www.securden.com
Author: Securden Dev
Author-email: devops-support@securden.com
License: MIT
Keywords: Securden,Securden SDK,Credential Retrieval APIs as functions
Classifier: Programming Language :: Python :: 3
Classifier: License :: OSI Approved :: MIT License
Classifier: Operating System :: OS Independent
Requires-Python: >= 3.8
Requires-Dist: urllib3==2.0.2
Requires-Dist: python-dateutil==2.9.0
Requires-Dist: pydantic==2.10.4
Requires-Dist: typing-extensions==4.12.2
Provides-Extra: dev
Requires-Dist: black; extra == "dev"
Requires-Dist: flake8; extra == "dev"
Requires-Dist: mypy; extra == "dev"
Provides-Extra: testing
Requires-Dist: pytest; extra == "testing"
Requires-Dist: pytest-cov; extra == "testing"
Requires-Dist: tox; extra == "testing"
